efetch/Debug.py
efetch/Fetch.py
efetch/Format.py
efetch/__init__.py
efetch/__main__.py
efetch/Art/__init__.py
efetch/Art/apple.py
efetch/Art/arch_big.py
efetch/Art/default.py
efetch/Art/gentoo.py
efetch/Art/kali.py
efetch/Art/macosx.py
efetch/Art/swastika.py
efetch/Art/swastika_no_unicode.py
efetch/Art/ubuntu.py
efetch/Art/unix_placeholder.py
efetch/Art/windows.py
efetch/Art/windows_8.py
efetch/Platform/Darwin.py
efetch/Platform/Linux.py
efetch/Platform/MacOSX.py
efetch/Platform/PlatformBase.py
efetch/Platform/Unix.py
efetch/Platform/Windows.py
efetch/Platform/__init__.py
efetch-0.1.0.dist-info/METADATA
efetch-0.1.0.dist-info/WHEEL
efetch-0.1.0.dist-info/entry_points.txt
efetch-0.1.0.dist-info/top_level.txt
efetch-0.1.0.dist-info/RECORD
