Metadata-Version: 2.4
Name: efetch
Version: 0.1.0
Summary: A BETTER LINUX FETCH - Forked from efetch, Upgraded to Py3!
Author: W0BBLEMASTER
License: MIT
Project-URL: Homepage, https://github.com/W0BBLEMASTER/PRJ_efetch
Requires-Dist: colorama
